cnd_lib/__init__.py
cnd_lib/__version__.py
cnd_lib/cli.py
cnd_lib/cnd_lib.py
cnd_lib-0.0.5.dist-info/METADATA
cnd_lib-0.0.5.dist-info/WHEEL
cnd_lib-0.0.5.dist-info/entry_points.txt
cnd_lib-0.0.5.dist-info/RECORD
